sc3nb/__init__.py
sc3nb/magics.py
sc3nb/process_handling.py
sc3nb/sc.py
sc3nb/sclang.py
sc3nb/timed_queue.py
sc3nb/util.py
sc3nb/version.py
sc3nb/osc/__init__.py
sc3nb/osc/osc_communication.py
sc3nb/osc/parsing.py
sc3nb/resources/__init__.py
sc3nb/resources/synthdefs/__init__.py
sc3nb/resources/synthdefs/pb-1ch.scsyndef
sc3nb/resources/synthdefs/pb-2ch.scsyndef
sc3nb/resources/synthdefs/record-1ch.scsyndef
sc3nb/resources/synthdefs/record-2ch.scsyndef
sc3nb/resources/synthdefs/s1.scsyndef
sc3nb/resources/synthdefs/s2.scsyndef
sc3nb/sc_objects/__init__.py
sc3nb/sc_objects/allocators.py
sc3nb/sc_objects/buffer.py
sc3nb/sc_objects/bus.py
sc3nb/sc_objects/node.py
sc3nb/sc_objects/recorder.py
sc3nb/sc_objects/score.py
sc3nb/sc_objects/server.py
sc3nb/sc_objects/synthdef.py
sc3nb/sc_objects/volume.py
sc3nb-1.1.0.dist-info/LICENSE
sc3nb-1.1.0.dist-info/METADATA
sc3nb-1.1.0.dist-info/WHEEL
sc3nb-1.1.0.dist-info/top_level.txt
sc3nb-1.1.0.dist-info/RECORD
