Metadata-Version: 2.1
Name: sc3nb
Version: 1.1.0
Summary: SuperCollider3 (sc3) for Python and Jupyter notebooks
Home-page: https://github.com/interactive-sonification/sc3nb
Author: Thomas Hermann
Author-email: thermann@techfak.uni-bielefeld.de
License: MIT
Project-URL: Documentation, https://interactive-sonification.github.io/sc3nb
Project-URL: Source Code, https://github.com/interactive-sonification/sc3nb
Project-URL: Bug Tracker, https://github.com/interactive-sonification/sc3nb/issues
Keywords: sonification,sound synthesis
Classifier: Development Status :: 4 - Beta
Classifier: License :: OSI Approved :: MIT License
Classifier: Programming Language :: Python :: 3
Classifier: Programming Language :: Python :: 3.6
Classifier: Programming Language :: Python :: 3.7
Classifier: Programming Language :: Python :: 3.8
Classifier: Programming Language :: Python :: 3.9
Classifier: Programming Language :: Other
Classifier: Operating System :: OS Independent
Classifier: Framework :: IPython
Classifier: Framework :: Jupyter
Classifier: Intended Audience :: Developers
Classifier: Intended Audience :: Education
Classifier: Intended Audience :: Information Technology
Classifier: Intended Audience :: Science/Research
Classifier: Topic :: Artistic Software
Classifier: Topic :: Multimedia :: Sound/Audio
Classifier: Topic :: Multimedia :: Sound/Audio :: Analysis
Classifier: Topic :: Multimedia :: Sound/Audio :: Sound Synthesis
Classifier: Topic :: Scientific/Engineering :: Human Machine Interfaces
Classifier: Topic :: Scientific/Engineering :: Visualization
Classifier: Topic :: Scientific/Engineering :: Information Analysis
Classifier: Topic :: Software Development :: Libraries :: Python Modules
License-File: LICENSE
Requires-Dist: pyamapping
Requires-Dist: psutil
Requires-Dist: python-osc >=1.7.4
Requires-Dist: numpy >=1.15.4
Requires-Dist: scipy >=1.3.1
Requires-Dist: ipython >=7.2.0
Requires-Dist: importlib-resources ; python_version < "3.9"
Provides-Extra: all
Requires-Dist: Sphinx ; extra == 'all'
Requires-Dist: sphinx-autoapi ; extra == 'all'
Requires-Dist: sphinx-rtd-theme ; extra == 'all'
Requires-Dist: nbsphinx ; extra == 'all'
Requires-Dist: nbsphinx-link ; extra == 'all'
Requires-Dist: nbstripout ; extra == 'all'
Requires-Dist: numpydoc ; extra == 'all'
Requires-Dist: jupyterlab ; extra == 'all'
Requires-Dist: matplotlib ; extra == 'all'
Requires-Dist: PyQt5 ; extra == 'all'
Requires-Dist: numpy ; extra == 'all'
Requires-Dist: myst-parser ; extra == 'all'
Requires-Dist: GitPython ; extra == 'all'
Requires-Dist: beautifulsoup4 ; extra == 'all'
Requires-Dist: pre-commit ; extra == 'all'
Requires-Dist: check-manifest ; extra == 'all'
Requires-Dist: black ; extra == 'all'
Requires-Dist: isort ; extra == 'all'
Requires-Dist: tox ; extra == 'all'
Requires-Dist: pytest ; extra == 'all'
Requires-Dist: pytest-cov ; extra == 'all'
Requires-Dist: pytest-xvfb ; (sys_platform == "linux") and extra == 'all'
Requires-Dist: PyQt5 ; (sys_platform == "linux") and extra == 'all'
Requires-Dist: pytest-qt ; (sys_platform == "linux") and extra == 'all'
Provides-Extra: dev
Requires-Dist: pre-commit ; extra == 'dev'
Requires-Dist: nbstripout ; extra == 'dev'
Requires-Dist: check-manifest ; extra == 'dev'
Requires-Dist: black ; extra == 'dev'
Requires-Dist: isort ; extra == 'dev'
Provides-Extra: docs
Requires-Dist: Sphinx ; extra == 'docs'
Requires-Dist: sphinx-autoapi ; extra == 'docs'
Requires-Dist: sphinx-rtd-theme ; extra == 'docs'
Requires-Dist: nbsphinx ; extra == 'docs'
Requires-Dist: nbsphinx-link ; extra == 'docs'
Requires-Dist: nbstripout ; extra == 'docs'
Requires-Dist: numpydoc ; extra == 'docs'
Requires-Dist: jupyterlab ; extra == 'docs'
Requires-Dist: matplotlib ; extra == 'docs'
Requires-Dist: PyQt5 ; extra == 'docs'
Requires-Dist: numpy ; extra == 'docs'
Requires-Dist: myst-parser ; extra == 'docs'
Requires-Dist: GitPython ; extra == 'docs'
Requires-Dist: beautifulsoup4 ; extra == 'docs'
Provides-Extra: localtest
Requires-Dist: pytest ; extra == 'localtest'
Requires-Dist: pytest-cov ; extra == 'localtest'
Requires-Dist: pytest-xvfb ; (sys_platform == "linux") and extra == 'localtest'
Requires-Dist: PyQt5 ; (sys_platform == "linux") and extra == 'localtest'
Requires-Dist: pytest-qt ; (sys_platform == "linux") and extra == 'localtest'
Provides-Extra: test
Requires-Dist: tox ; extra == 'test'
